yated/__init__.py
yated/__main__.py
yated/clip.py
yated/config.py
yated/dialogs.py
yated/doc.py
yated/menus.py
yated/ptypes.py
yated/utils.py
yated/view.py
yated/yated.py
yated/__pycache__/__init__.cpython-312.pyc
yated/__pycache__/clip.cpython-312.pyc
yated/__pycache__/config.cpython-312.pyc
yated/__pycache__/dialogs.cpython-312.pyc
yated/__pycache__/doc.cpython-312.pyc
yated/__pycache__/menus.cpython-312.pyc
yated/__pycache__/ptypes.cpython-312.pyc
yated/__pycache__/utils.cpython-312.pyc
yated/__pycache__/view.cpython-312.pyc
yated/__pycache__/yated.cpython-312.pyc
yated-1.2.1.dist-info/licenses/LICENSE
yated-1.2.1.dist-info/METADATA
yated-1.2.1.dist-info/WHEEL
yated-1.2.1.dist-info/entry_points.txt
yated-1.2.1.dist-info/top_level.txt
yated-1.2.1.dist-info/RECORD
