Metadata-Version: 2.4
Name: yated
Version: 1.2.1
Summary: A terminal based text editor
Author-email: Amir Geva <amirgeva@gmail.com>
License:                     GNU GENERAL PUBLIC LICENSE
Project-URL: Homepage, https://github.com/amirgeva/yated
Project-URL: Repository, https://github.com/amirgeva/yated
Project-URL: Issues, https://github.com/amirgeva/yated/issues
Keywords: terminal,text editor
Classifier: Development Status :: 4 - Beta
Classifier: Intended Audience :: Developers
Classifier: Topic :: Text Editors
Classifier: License :: OSI Approved :: GNU General Public License v3 (GPLv3)
Classifier: Programming Language :: Python :: 3
Classifier: Programming Language :: Python :: 3 :: Only
Classifier: Programming Language :: Python :: 3.8
Classifier: Programming Language :: Python :: 3.9
Classifier: Programming Language :: Python :: 3.10
Classifier: Programming Language :: Python :: 3.11
Classifier: Programming Language :: Python :: 3.12
Requires-Python: >=3.8
License-File: LICENSE
Dynamic: license-file
